dmlc_tracker/__init__.py
dmlc_tracker/kubernetes.py
dmlc_tracker/launcher.py
dmlc_tracker/local.py
dmlc_tracker/mesos.py
dmlc_tracker/mpi.py
dmlc_tracker/opts.py
dmlc_tracker/sge.py
dmlc_tracker/slurm.py
dmlc_tracker/ssh.py
dmlc_tracker/submit.py
dmlc_tracker/tracker.py
dmlc_tracker/yarn.py
mxnet/COMMIT_HASH
mxnet/__init__.py
mxnet/attribute.py
mxnet/autograd.py
mxnet/base.py
mxnet/callback.py
mxnet/context.py
mxnet/engine.py
mxnet/executor.py
mxnet/executor_manager.py
mxnet/initializer.py
mxnet/kvstore.py
mxnet/kvstore_server.py
mxnet/libgfortran.so.3
mxnet/libinfo.py
mxnet/libmxnet.so
mxnet/libquadmath.so.0
mxnet/log.py
mxnet/lr_scheduler.py
mxnet/metric.py
mxnet/misc.py
mxnet/model.py
mxnet/monitor.py
mxnet/name.py
mxnet/ndarray_doc.py
mxnet/operator.py
mxnet/profiler.py
mxnet/random.py
mxnet/recordio.py
mxnet/registry.py
mxnet/rtc.py
mxnet/symbol_doc.py
mxnet/test_utils.py
mxnet/torch.py
mxnet/util.py
mxnet/visualization.py
mxnet/_ctypes/__init__.py
mxnet/_ctypes/ndarray.py
mxnet/_ctypes/symbol.py
mxnet/_cy2/__init__.py
mxnet/_cy3/__init__.py
mxnet/contrib/__init__.py
mxnet/contrib/autograd.py
mxnet/contrib/io.py
mxnet/contrib/ndarray.py
mxnet/contrib/quantization.py
mxnet/contrib/symbol.py
mxnet/contrib/tensorboard.py
mxnet/contrib/tensorrt.py
mxnet/contrib/onnx/__init__.py
mxnet/contrib/onnx/mx2onnx/__init__.py
mxnet/contrib/onnx/mx2onnx/_export_helper.py
mxnet/contrib/onnx/mx2onnx/_op_translations.py
mxnet/contrib/onnx/mx2onnx/export_model.py
mxnet/contrib/onnx/mx2onnx/export_onnx.py
mxnet/contrib/onnx/onnx2mx/__init__.py
mxnet/contrib/onnx/onnx2mx/_import_helper.py
mxnet/contrib/onnx/onnx2mx/_op_translations.py
mxnet/contrib/onnx/onnx2mx/_translation_utils.py
mxnet/contrib/onnx/onnx2mx/import_model.py
mxnet/contrib/onnx/onnx2mx/import_onnx.py
mxnet/contrib/onnx/onnx2mx/import_to_gluon.py
mxnet/contrib/svrg_optimization/__init__.py
mxnet/contrib/svrg_optimization/svrg_module.py
mxnet/contrib/svrg_optimization/svrg_optimizer.py
mxnet/contrib/text/__init__.py
mxnet_gcc5-1.4.0.dist-info/METADATA
mxnet_gcc5-1.4.0.dist-info/WHEEL
mxnet_gcc5-1.4.0.dist-info/top_level.txt
mxnet_gcc5-1.4.0.dist-info/RECORD
